Workbook

Sheet Invoice Tracker
A1: Invoice ID | B1: Vendor Name | C1: Invoice Number | D1: Invoice Amount | E1: Department | F1: Invoice Type | G1: PO Number | H1: Approver | I1: Approval Level | J1: Date Received | K1: Payment Terms | L1: Payment Due Date | M1: Status | N1: Exception Type | O1: Approval Date | P1: Payment Date | Q1: Invoice Age Days | R1: Approval Cycle Days | S1: Days Until Due | T1: Overdue Approval Flag | U1: Late Payment Risk | V1: Comments
A2: NS-202606-0001 | B2: Union Energy Services | C2: INV-343962 | D2: 1501.38 | E2: Maintenance | F2: PO | G2: PO-78265 | H2: Marcus Lee | I2: Department Manager | J2: 46150 | K2: Net 15 | L2: 46165 | M2: Paid | N2: None | O2: 46152 | P2: 46154 | Q2: =IF(J2="","",TODAY()-J2) -> 39 | R2: =IF(O2="","",O2-J2) -> 2 | S2: =IF(L2="","",L2-TODAY()) -> -24 | T2: =IF(AND(M2="Pending Approval",Q2>5),"Overdue","On Track") -> On Track | U2: =IF(AND(M2<>"Paid",S2<=5),"At Risk","Normal") -> Normal | V2: Payment completed
A3: NS-202606-0002 | B3: Quarry Equipment Rental | C3: INV-456778 | D3: 1154.71 | E3: HR | F3: Non-PO | H3: Ava Johnson | I3: Department Manager | J3: 46178 | K3: 2/10 Net 30 | L3: 46208 | M3: Pending Approval | N3: None | Q3: =IF(J3="","",TODAY()-J3) -> 11 | R3: =IF(O3="","",O3-J3) | S3: =IF(L3="","",L3-TODAY()) -> 19 | T3: =IF(AND(M3="Pending Approval",Q3>5),"Overdue","On Track") -> Overdue | U3: =IF(AND(M3<>"Paid",S3<=5),"At Risk","Normal") -> Normal | V3: Awaiting manager/director action
A4: NS-202606-0003 | B4: IronGate Components | C4: INV-662275 | D4: 3723.9 | E4: Procurement | F4: PO | G4: PO-54898 | H4: Nina Patel | I4: Department Manager | J4: 46150 | K4: Net 45 | L4: 46195 | M4: Paid | N4: Missing Documentation | O4: 46164 | P4: 46168 | Q4: =IF(J4="","",TODAY()-J4) -> 39 | R4: =IF(O4="","",O4-J4) -> 14 | S4: =IF(L4="","",L4-TODAY()) -> 6 | T4: =IF(AND(M4="Pending Approval",Q4>5),"Overdue","On Track") -> On Track | U4: =IF(AND(M4<>"Paid",S4<=5),"At Risk","Normal") -> Normal | V4: Exception review required: Missing Documentation
A5: NS-202606-0004 | B5: Delta Tooling | C5: INV-498591 | D5: 1583.96 | E5: Engineering | F5: Non-PO | H5: Maya Singh | I5: Department Manager | J5: 46167 | K5: Net 30 | L5: 46197 | M5: Paid | N5: Missing PO | O5: 46182 | P5: 46183 | Q5: =IF(J5="","",TODAY()-J5) -> 22 | R5: =IF(O5="","",O5-J5) -> 15 | S5: =IF(L5="","",L5-TODAY()) -> 8 | T5: =IF(AND(M5="Pending Approval",Q5>5),"Overdue","On Track") -> On Track | U5: =IF(AND(M5<>"Paid",S5<=5),"At Risk","Normal") -> Normal | V5: Exception review required: Missing PO
A6: NS-202606-0005 | B6: IronGate Components | C6: INV-279451 | D6: 1909.99 | E6: Facilities | F6: PO | G6: PO-43730 | H6: Grace Morgan | I6: Department Manager | J6: 46186 | K6: Net 45 | L6: 46231 | M6: Exception | N6: None | Q6: =IF(J6="","",TODAY()-J6) -> 3 | R6: =IF(O6="","",O6-J6) | S6: =IF(L6="","",L6-TODAY()) -> 42 | T6: =IF(AND(M6="Pending Approval",Q6>5),"Overdue","On Track") -> On Track | U6: =IF(AND(M6<>"Paid",S6<=5),"At Risk","Normal") -> Normal
A7: NS-202606-0006 | B7: Ridgeway Plastics | C7: INV-133659 | D7: 2353.28 | E7: Sales | F7: PO | G7: PO-71943 | H7: Ryan Scott | I7: Department Manager | J7: 46188 | K7: Net 30 | L7: 46218 | M7: Pending Approval | N7: None | Q7: =IF(J7="","",TODAY()-J7) -> 1 | R7: =IF(O7="","",O7-J7) | S7: =IF(L7="","",L7-TODAY()) -> 29 | T7: =IF(AND(M7="Pending Approval",Q7>5),"Overdue","On Track") -> On Track | U7: =IF(AND(M7<>"Paid",S7<=5),"At Risk","Normal") -> Normal | V7: Awaiting manager/director action
A8: NS-202606-0007 | B8: Keystone Electrical | C8: INV-358607 | D8: 1209.97 | E8: Engineering | F8: Non-PO | H8: Maya Singh | I8: Department Manager | J8: 46189 | K8: Net 45 | L8: 46234 | M8: Pending Approval | N8: None | Q8: =IF(J8="","",TODAY()-J8) -> 0 | R8: =IF(O8="","",O8-J8) | S8: =IF(L8="","",L8-TODAY()) -> 45 | T8: =IF(AND(M8="Pending Approval",Q8>5),"Overdue","On Track") -> On Track | U8: =IF(AND(M8<>"Paid",S8<=5),"At Risk","Normal") -> Normal | V8: Awaiting manager/director action
A9: NS-202606-0008 | B9: Zenith Software | C9: INV-892495 | D9: 3648.91 | E9: IT | F9: PO | G9: PO-68242 | H9: Noah Bennett | I9: Department Manager | J9: 46169 | K9: Net 45 | L9: 46214 | M9: Paid | N9: None | O9: 46172 | P9: 46173 | Q9: =IF(J9="","",TODAY()-J9) -> 20 | R9: =IF(O9="","",O9-J9) -> 3 | S9: =IF(L9="","",L9-TODAY()) -> 25 | T9: =IF(AND(M9="Pending Approval",Q9>5),"Overdue","On Track") -> On Track | U9: =IF(AND(M9<>"Paid",S9<=5),"At Risk","Normal") -> Normal | V9: Payment completed
A10: NS-202606-0009 | B10: BlueLine Logistics | C10: INV-813328 | D10: 977.92 | E10: Maintenance | F10: Non-PO | H10: Marcus Lee | I10: Department Manager | J10: 46182 | K10: Net 15 | L10: 46197 | M10: Rejected | N10: None | O10: 46184 | Q10: =IF(J10="","",TODAY()-J10) -> 7 | R10: =IF(O10="","",O10-J10) -> 2 | S10: =IF(L10="","",L10-TODAY()) -> 8 | T10: =IF(AND(M10="Pending Approval",Q10>5),"Overdue","On Track") -> On Track | U10: =IF(AND(M10<>"Paid",S10<=5),"At Risk","Normal") -> Normal
A11: NS-202606-0010 | B11: Zenith Software | C11: INV-854639 | D11: 2693.22 | E11: Maintenance | F11: PO | G11: PO-72006 | H11: Marcus Lee | I11: Department Manager | J11: 46165 | K11: Net 15 | L11: 46180 | M11: Paid | N11: None | O11: 46170 | P11: 46176 | Q11: =IF(J11="","",TODAY()-J11) -> 24 | R11: =IF(O11="","",O11-J11) -> 5 | S11: =IF(L11="","",L11-TODAY()) -> -9 | T11: =IF(AND(M11="Pending Approval",Q11>5),"Overdue","On Track") -> On Track | U11: =IF(AND(M11<>"Paid",S11<=5),"At Risk","Normal") -> Normal | V11: Payment completed
A12: NS-202606-0011 | B12: IronGate Components | C12: INV-656116 | D12: 14899.79 | E12: IT | F12: PO | G12: PO-70979 | H12: Monica Price | I12: Director | J12: 46163 | K12: Net 30 | L12: 46193 | M12: Paid | N12: None | O12: 46166 | P12: 46173 | Q12: =IF(J12="","",TODAY()-J12) -> 26 | R12: =IF(O12="","",O12-J12) -> 3 | S12: =IF(L12="","",L12-TODAY()) -> 4 | T12: =IF(AND(M12="Pending Approval",Q12>5),"Overdue","On Track") -> On Track | U12: =IF(AND(M12<>"Paid",S12<=5),"At Risk","Normal") -> Normal | V12: Payment completed
A13: NS-202606-0012 | B13: Apex Industrial Supply | C13: INV-172574 | D13: 338.62 | E13: HR | F13: Non-PO | H13: Ava Johnson | I13: Department Manager | J13: 46163 | K13: Net 30 | L13: 46193 | M13: Paid | N13: None | O13: 46166 | P13: 46173 | Q13: =IF(J13="","",TODAY()-J13) -> 26 | R13: =IF(O13="","",O13-J13) -> 3 | S13: =IF(L13="","",L13-TODAY()) -> 4 | T13: =IF(AND(M13="Pending Approval",Q13>5),"Overdue","On Track") -> On Track | U13: =IF(AND(M13<>"Paid",S13<=5),"At Risk","Normal") -> Normal | V13: Payment completed
A14: NS-202606-0013 | B14: Ridgeway Plastics | C14: INV-781446 | D14: 2412.53 | E14: Procurement | F14: PO | G14: PO-47370 | H14: Nina Patel | I14: Department Manager | J14: 46177 | K14: 2/10 Net 30 | L14: 46207 | M14: Sent to Accounting | N14: Unclear Department Ownership | O14: 46189 | Q14: =IF(J14="","",TODAY()-J14) -> 12 | R14: =IF(O14="","",O14-J14) -> 12 | S14: =IF(L14="","",L14-TODAY()) -> 18 | T14: =IF(AND(M14="Pending Approval",Q14>5),"Overdue","On Track") -> On Track | U14: =IF(AND(M14<>"Paid",S14<=5),"At Risk","Normal") -> Normal | V14: Exception review required: Unclear Department Ownership
A15: NS-202606-0014 | B15: Lakeview Chemicals | C15: INV-174441 | D15: 13803.98 | E15: Facilities | F15: PO | G15: PO-34196 | H15: Victor Allen | I15: Director | J15: 46165 | K15: Net 15 | L15: 46180 | M15: Paid | N15: None | O15: 46172 | P15: 46187 | Q15: =IF(J15="","",TODAY()-J15) -> 24 | R15: =IF(O15="","",O15-J15) -> 7 | S15: =IF(L15="","",L15-TODAY()) -> -9 | T15: =IF(AND(M15="Pending Approval",Q15>5),"Overdue","On Track") -> On Track | U15: =IF(AND(M15<>"Paid",S15<=5),"At Risk","Normal") -> Normal | V15: Paid late due to approval bottleneck
A16: NS-202606-0015 | B16: WestBridge Staffing | C16: INV-858490 | D16: 556.67 | E16: Finance | F16: PO | G16: PO-51654 | H16: Evelyn Carter | I16: Department Manager | J16: 46148 | K16: Net 30 | L16: 46178 | M16: Paid | N16: None | O16: 46156 | P16: 46158 | Q16: =IF(J16="","",TODAY()-J16) -> 41 | R16: =IF(O16="","",O16-J16) -> 8 | S16: =IF(L16="","",L16-TODAY()) -> -11 | T16: =IF(AND(M16="Pending Approval",Q16>5),"Overdue","On Track") -> On Track | U16: =IF(AND(M16<>"Paid",S16<=5),"At Risk","Normal") -> Normal | V16: Payment completed
A17: NS-202606-0016 | B17: Summit Security | C17: INV-156802 | D17: 3820.02 | E17: HR | F17: Non-PO | H17: Ava Johnson | I17: Department Manager | J17: 46156 | K17: Net 15 | L17: 46171 | M17: Paid | N17: None | O17: 46167 | P17: 46173 | Q17: =IF(J17="","",TODAY()-J17) -> 33 | R17: =IF(O17="","",O17-J17) -> 11 | S17: =IF(L17="","",L17-TODAY()) -> -18 | T17: =IF(AND(M17="Pending Approval",Q17>5),"Overdue","On Track") -> On Track | U17: =IF(AND(M17<>"Paid",S17<=5),"At Risk","Normal") -> Normal | V17: Payment completed
A18: NS-202606-0017 | B18: Vector Calibration | C18: INV-392075 | D18: 32340.04 | E18: Finance | F18: PO | G18: PO-52236 | H18: Jordan Blake | I18: Finance Director | J18: 46150 | K18: Net 30 | L18: 46180 | M18: Paid | N18: None | O18: 46162 | P18: 46164 | Q18: =IF(J18="","",TODAY()-J18) -> 39 | R18: =IF(O18="","",O18-J18) -> 12 | S18: =IF(L18="","",L18-TODAY()) -> -9 | T18: =IF(AND(M18="Pending Approval",Q18>5),"Overdue","On Track") -> On Track | U18: =IF(AND(M18<>"Paid",S18<=5),"At Risk","Normal") -> Normal | V18: Payment completed
A19: NS-202606-0018 | B19: Orion Consulting | C19: INV-989921 | D19: 6470.01 | E19: Production | F19: Non-PO | H19: Heather King | I19: Director | J19: 46179 | K19: Net 15 | L19: 46194 | M19: Exception | N19: None | Q19: =IF(J19="","",TODAY()-J19) -> 10 | R19: =IF(O19="","",O19-J19) | S19: =IF(L19="","",L19-TODAY()) -> 5 | T19: =IF(AND(M19="Pending Approval",Q19>5),"Overdue","On Track") -> On Track | U19: =IF(AND(M19<>"Paid",S19<=5),"At Risk","Normal") -> At Risk
A20: NS-202606-0019 | B20: Harbor Freight Services | C20: INV-865990 | D20: 2440.18 | E20: Procurement | F20: Non-PO | H20: Nina Patel | I20: Department Manager | J20: 46147 | K20: Net 30 | L20: 46177 | M20: Paid | N20: None | O20: 46156 | P20: 46162 | Q20: =IF(J20="","",TODAY()-J20) -> 42 | R20: =IF(O20="","",O20-J20) -> 9 | S20: =IF(L20="","",L20-TODAY()) -> -12 | T20: =IF(AND(M20="Pending Approval",Q20>5),"Overdue","On Track") -> On Track | U20: =IF(AND(M20<>"Paid",S20<=5),"At Risk","Normal") -> Normal | V20: Payment completed
A21: NS-202606-0020 | B21: Ridgeway Plastics | C21: INV-627276 | D21: 954.33 | E21: Finance | F21: PO | G21: PO-33832 | H21: Evelyn Carter | I21: Department Manager | J21: 46181 | K21: Net 15 | L21: 46196 | M21: Paid | N21: None | O21: 46182 | P21: 46186 | Q21: =IF(J21="","",TODAY()-J21) -> 8 | R21: =IF(O21="","",O21-J21) -> 1 | S21: =IF(L21="","",L21-TODAY()) -> 7 | T21: =IF(AND(M21="Pending Approval",Q21>5),"Overdue","On Track") -> On Track | U21: =IF(AND(M21<>"Paid",S21<=5),"At Risk","Normal") -> Normal | V21: Payment completed
A22: NS-202606-0021 | B22: Quarry Equipment Rental | C22: INV-749468 | D22: 2560.62 | E22: Procurement | F22: Non-PO | H22: Nina Patel | I22: Department Manager | J22: 46148 | K22: Net 15 | L22: 46163 | M22: Paid | N22: None | O22: 46152 | P22: 46153 | Q22: =IF(J22="","",TODAY()-J22) -> 41 | R22: =IF(O22="","",O22-J22) -> 4 | S22: =IF(L22="","",L22-TODAY()) -> -26 | T22: =IF(AND(M22="Pending Approval",Q22>5),"Overdue","On Track") -> On Track | U22: =IF(AND(M22<>"Paid",S22<=5),"At Risk","Normal") -> Normal | V22: Payment completed
A23: NS-202606-0022 | B23: Cedar Packaging Co. | C23: INV-414569 | D23: 2821.78 | E23: Engineering | F23: PO | G23: PO-47089 | H23: Maya Singh | I23: Department Manager | J23: 46157 | K23: Net 45 | L23: 46202 | M23: Paid | N23: None | O23: 46164 | P23: 46170 | Q23: =IF(J23="","",TODAY()-J23) -> 32 | R23: =IF(O23="","",O23-J23) -> 7 | S23: =IF(L23="","",L23-TODAY()) -> 13 | T23: =IF(AND(M23="Pending Approval",Q23>5),"Overdue","On Track") -> On Track | U23: =IF(AND(M23<>"Paid",S23<=5),"At Risk","Normal") -> Normal | V23: Payment completed
A24: NS-202606-0023 | B24: Orion Consulting | C24: INV-238890 | D24: 23246.82 | E24: Logistics | F24: PO | G24: PO-70708 | H24: Anthony Ross | I24: Director | J24: 46180 | K24: Net 15 | L24: 46195 | M24: Approved | N24: None | O24: 46184 | Q24: =IF(J24="","",TODAY()-J24) -> 9 | R24: =IF(O24="","",O24-J24) -> 4 | S24: =IF(L24="","",L24-TODAY()) -> 6 | T24: =IF(AND(M24="Pending Approval",Q24>5),"Overdue","On Track") -> On Track | U24: =IF(AND(M24<>"Paid",S24<=5),"At Risk","Normal") -> Normal
A25: NS-202606-0024 | B25: Lakeview Chemicals | C25: INV-681542 | D25: 12205.78 | E25: Maintenance | F25: PO | G25: PO-84640 | H25: Priya Shah | I25: Director | J25: 46178 | K25: Net 45 | L25: 46223 | M25: Pending Approval | N25: None | Q25: =IF(J25="","",TODAY()-J25) -> 11 | R25: =IF(O25="","",O25-J25) | S25: =IF(L25="","",L25-TODAY()) -> 34 | T25: =IF(AND(M25="Pending Approval",Q25>5),"Overdue","On Track") -> Overdue | U25: =IF(AND(M25<>"Paid",S25<=5),"At Risk","Normal") -> Normal | V25: Awaiting manager/director action
A26: NS-202606-0025 | B26: Juniper Office Supply | C26: INV-820892 | D26: 4245.48 | E26: Finance | F26: PO | G26: PO-88308 | H26: Evelyn Carter | I26: Department Manager | J26: 46150 | K26: Net 30 | L26: 46180 | M26: Paid | N26: None | O26: 46154 | P26: 46182 | Q26: =IF(J26="","",TODAY()-J26) -> 39 | R26: =IF(O26="","",O26-J26) -> 4 | S26: =IF(L26="","",L26-TODAY()) -> -9 | T26: =IF(AND(M26="Pending Approval",Q26>5),"Overdue","On Track") -> On Track | U26: =IF(AND(M26<>"Paid",S26<=5),"At Risk","Normal") -> Normal | V26: Paid late due to approval bottleneck
A27: NS-202606-0026 | B27: Union Energy Services | C27: INV-768061 | D27: 1392.6 | E27: Quality | F27: Non-PO | H27: Lena Ortiz | I27: Department Manager | J27: 46147 | K27: Net 15 | L27: 46162 | M27: Paid | N27: None | O27: 46149 | P27: 46151 | Q27: =IF(J27="","",TODAY()-J27) -> 42 | R27: =IF(O27="","",O27-J27) -> 2 | S27: =IF(L27="","",L27-TODAY()) -> -27 | T27: =IF(AND(M27="Pending Approval",Q27>5),"Overdue","On Track") -> On Track | U27: =IF(AND(M27<>"Paid",S27<=5),"At Risk","Normal") -> Normal | V27: Payment completed
A28: NS-202606-0027 | B28: IronGate Components | C28: INV-710805 | D28: 15757.77 | E28: Procurement | F28: PO | G28: PO-30633 | H28: Carlos Mendes | I28: Director | J28: 46151 | K28: Net 15 | L28: 46166 | M28: Paid | N28: Unclear Department Ownership | O28: 46161 | P28: 46164 | Q28: =IF(J28="","",TODAY()-J28) -> 38 | R28: =IF(O28="","",O28-J28) -> 10 | S28: =IF(L28="","",L28-TODAY()) -> -23 | T28: =IF(AND(M28="Pending Approval",Q28>5),"Overdue","On Track") -> On Track | U28: =IF(AND(M28<>"Paid",S28<=5),"At Risk","Normal") -> Normal | V28: Exception review required: Unclear Department Ownership
A29: NS-202606-0028 | B29: Ridgeway Plastics | C29: INV-918011 | D29: 440.32 | E29: Procurement | F29: PO | G29: PO-82174 | H29: Nina Patel | I29: Department Manager | J29: 46146 | K29: Net 45 | L29: 46191 | M29: Paid | N29: None | O29: 46150 | P29: 46153 | Q29: =IF(J29="","",TODAY()-J29) -> 43 | R29: =IF(O29="","",O29-J29) -> 4 | S29: =IF(L29="","",L29-TODAY()) -> 2 | T29: =IF(AND(M29="Pending Approval",Q29>5),"Overdue","On Track") -> On Track | U29: =IF(AND(M29<>"Paid",S29<=5),"At Risk","Normal") -> Normal | V29: Payment completed
A30: NS-202606-0029 | B30: Ridgeway Plastics | C30: INV-920391 | D30: 77588.69 | E30: Engineering | F30: Non-PO | H30: Jordan Blake | I30: Finance Director | J30: 46159 | K30: Net 30 | L30: 46189 | M30: Paid | N30: Unclear Department Ownership | O30: 46173 | P30: 46176 | Q30: =IF(J30="","",TODAY()-J30) -> 30 | R30: =IF(O30="","",O30-J30) -> 14 | S30: =IF(L30="","",L30-TODAY()) -> 0 | T30: =IF(AND(M30="Pending Approval",Q30>5),"Overdue","On Track") -> On Track | U30: =IF(AND(M30<>"Paid",S30<=5),"At Risk","Normal") -> Normal | V30: Exception review required: Unclear Department Ownership
A31: NS-202606-0030 | B31: Northfield Metals | C31: INV-333238 | D31: 20809.61 | E31: Finance | F31: PO | G31: PO-81601 | H31: Finance Director | I31: Director | J31: 46188 | K31: Net 15 | L31: 46203 | M31: Approved | N31: None | O31: 46189 | Q31: =IF(J31="","",TODAY()-J31) -> 1 | R31: =IF(O31="","",O31-J31) -> 1 | S31: =IF(L31="","",L31-TODAY()) -> 14 | T31: =IF(AND(M31="Pending Approval",Q31>5),"Overdue","On Track") -> On Track | U31: =IF(AND(M31<>"Paid",S31<=5),"At Risk","Normal") -> Normal
A32: NS-202606-0031 | B32: Granite Safety Supply | C32: INV-392683 | D32: 3983.44 | E32: Facilities | F32: Non-PO | H32: Grace Morgan | I32: Department Manager | J32: 46158 | K32: Net 15 | L32: 46173 | M32: Exception | N32: None | Q32: =IF(J32="","",TODAY()-J32) -> 31 | R32: =IF(O32="","",O32-J32) | S32: =IF(L32="","",L32-TODAY()) -> -16 | T32: =IF(AND(M32="Pending Approval",Q32>5),"Overdue","On Track") -> On Track | U32: =IF(AND(M32<>"Paid",S32<=5),"At Risk","Normal") -> At Risk
A33: NS-202606-0032 | B33: Lakeview Chemicals | C33: INV-555673 | D33: 3341.81 | E33: Finance | F33: Non-PO | H33: Evelyn Carter | I33: Department Manager | J33: 46165 | K33: Net 15 | L33: 46180 | M33: Paid | N33: None | O33: 46171 | P33: 46176 | Q33: =IF(J33="","",TODAY()-J33) -> 24 | R33: =IF(O33="","",O33-J33) -> 6 | S33: =IF(L33="","",L33-TODAY()) -> -9 | T33: =IF(AND(M33="Pending Approval",Q33>5),"Overdue","On Track") -> On Track | U33: =IF(AND(M33<>"Paid",S33<=5),"At Risk","Normal") -> Normal | V33: Payment completed
A34: NS-202606-0033 | B34: Lakeview Chemicals | C34: INV-645175 | D34: 13509.68 | E34: Sales | F34: Non-PO | H34: Michelle Young | I34: Director | J34: 46151 | K34: 2/10 Net 30 | L34: 46181 | M34: Paid | N34: Incorrect Vendor Information | O34: 46161 | P34: 46162 | Q34: =IF(J34="","",TODAY()-J34) -> 38 | R34: =IF(O34="","",O34-J34) -> 10 | S34: =IF(L34="","",L34-TODAY()) -> -8 | T34: =IF(AND(M34="Pending Approval",Q34>5),"Overdue","On Track") -> On Track | U34: =IF(AND(M34<>"Paid",S34<=5),"At Risk","Normal") -> Normal | V34: Exception review required: Incorrect Vendor Information
A35: NS-202606-0034 | B35: Ridgeway Plastics | C35: INV-854717 | D35: 3625.87 | E35: Finance | F35: Non-PO | H35: Evelyn Carter | I35: Department Manager | J35: 46167 | K35: 2/10 Net 30 | L35: 46197 | M35: Paid | N35: None | O35: 46176 | P35: 46177 | Q35: =IF(J35="","",TODAY()-J35) -> 22 | R35: =IF(O35="","",O35-J35) -> 9 | S35: =IF(L35="","",L35-TODAY()) -> 8 | T35: =IF(AND(M35="Pending Approval",Q35>5),"Overdue","On Track") -> On Track | U35: =IF(AND(M35<>"Paid",S35<=5),"At Risk","Normal") -> Normal | V35: Payment completed
A36: NS-202606-0035 | B36: Juniper Office Supply | C36: INV-282480 | D36: 2108.19 | E36: IT | F36: PO | G36: PO-49376 | H36: Noah Bennett | I36: Department Manager | J36: 46179 | K36: Net 30 | L36: 46209 | M36: Pending Approval | N36: None | Q36: =IF(J36="","",TODAY()-J36) -> 10 | R36: =IF(O36="","",O36-J36) | S36: =IF(L36="","",L36-TODAY()) -> 20 | T36: =IF(AND(M36="Pending Approval",Q36>5),"Overdue","On Track") -> Overdue | U36: =IF(AND(M36<>"Paid",S36<=5),"At Risk","Normal") -> Normal | V36: Awaiting manager/director action
A37: NS-202606-0036 | B37: Titan Machine Parts | C37: INV-808446 | D37: 2743.11 | E37: HR | F37: PO | G37: PO-48803 | H37: Ava Johnson | I37: Department Manager | J37: 46157 | K37: 2/10 Net 30 | L37: 46187 | M37: Paid | N37: None | O37: 46163 | P37: 46167 | Q37: =IF(J37="","",TODAY()-J37) -> 32 | R37: =IF(O37="","",O37-J37) -> 6 | S37: =IF(L37="","",L37-TODAY()) -> -2 | T37: =IF(AND(M37="Pending Approval",Q37>5),"Overdue","On Track") -> On Track | U37: =IF(AND(M37<>"Paid",S37<=5),"At Risk","Normal") -> Normal | V37: Payment completed
A38: NS-202606-0037 | B38: Granite Safety Supply | C38: INV-887625 | D38: 4350.37 | E38: IT | F38: Non-PO | H38: Noah Bennett | I38: Department Manager | J38: 46154 | K38: Net 15 | L38: 46169 | M38: Sent to Accounting | N38: None | O38: 46161 | Q38: =IF(J38="","",TODAY()-J38) -> 35 | R38: =IF(O38="","",O38-J38) -> 7 | S38: =IF(L38="","",L38-TODAY()) -> -20 | T38: =IF(AND(M38="Pending Approval",Q38>5),"Overdue","On Track") -> On Track | U38: =IF(AND(M38<>"Paid",S38<=5),"At Risk","Normal") -> At Risk
A39: NS-202606-0038 | B39: Harbor Freight Services | C39: INV-703634 | D39: 3919.86 | E39: Finance | F39: PO | G39: PO-33028 | H39: Evelyn Carter | I39: Department Manager | J39: 46159 | K39: 2/10 Net 30 | L39: 46189 | M39: Paid | N39: None | O39: 46161 | P39: 46194 | Q39: =IF(J39="","",TODAY()-J39) -> 30 | R39: =IF(O39="","",O39-J39) -> 2 | S39: =IF(L39="","",L39-TODAY()) -> 0 | T39: =IF(AND(M39="Pending Approval",Q39>5),"Overdue","On Track") -> On Track | U39: =IF(AND(M39<>"Paid",S39<=5),"At Risk","Normal") -> Normal | V39: Paid late due to approval bottleneck
A40: NS-202606-0039 | B40: Granite Safety Supply | C40: INV-284430 | D40: 2499.42 | E40: Sales | F40: PO | G40: PO-72995 | H40: Ryan Scott | I40: Department Manager | J40: 46188 | K40: Net 15 | L40: 46203 | M40: Pending Approval | N40: Incorrect Vendor Information | Q40: =IF(J40="","",TODAY()-J40) -> 1 | R40: =IF(O40="","",O40-J40) | S40: =IF(L40="","",L40-TODAY()) -> 14 | T40: =IF(AND(M40="Pending Approval",Q40>5),"Overdue","On Track") -> On Track | U40: =IF(AND(M40<>"Paid",S40<=5),"At Risk","Normal") -> Normal | V40: Exception review required: Incorrect Vendor Information
A41: NS-202606-0040 | B41: WestBridge Staffing | C41: INV-629298 | D41: 2786.2 | E41: IT | F41: Non-PO | H41: Noah Bennett | I41: Department Manager | J41: 46151 | K41: 2/10 Net 30 | L41: 46181 | M41: Paid | N41: None | O41: 46161 | P41: 46167 | Q41: =IF(J41="","",TODAY()-J41) -> 38 | R41: =IF(O41="","",O41-J41) -> 10 | S41: =IF(L41="","",L41-TODAY()) -> -8 | T41: =IF(AND(M41="Pending Approval",Q41>5),"Overdue","On Track") -> On Track | U41: =IF(AND(M41<>"Paid",S41<=5),"At Risk","Normal") -> Normal | V41: Payment completed
A42: NS-202606-0041 | B42: Northfield Metals | C42: INV-181247 | D42: 974.17 | E42: IT | F42: Non-PO | H42: Noah Bennett | I42: Department Manager | J42: 46172 | K42: Net 45 | L42: 46217 | M42: Sent to Accounting | N42: Missing PO | O42: 46189 | Q42: =IF(J42="","",TODAY()-J42) -> 17 | R42: =IF(O42="","",O42-J42) -> 17 | S42: =IF(L42="","",L42-TODAY()) -> 28 | T42: =IF(AND(M42="Pending Approval",Q42>5),"Overdue","On Track") -> On Track | U42: =IF(AND(M42<>"Paid",S42<=5),"At Risk","Normal") -> Normal | V42: Exception review required: Missing PO
A43: NS-202606-0042 | B43: WestBridge Staffing | C43: INV-446954 | D43: 1778.11 | E43: Quality | F43: Non-PO | H43: Lena Ortiz | I43: Department Manager | J43: 46149 | K43: Net 30 | L43: 46179 | M43: Paid | N43: None | O43: 46154 | P43: 46158 | Q43: =IF(J43="","",TODAY()-J43) -> 40 | R43: =IF(O43="","",O43-J43) -> 5 | S43: =IF(L43="","",L43-TODAY()) -> -10 | T43: =IF(AND(M43="Pending Approval",Q43>5),"Overdue","On Track") -> On Track | U43: =IF(AND(M43<>"Paid",S43<=5),"At Risk","Normal") -> Normal | V43: Payment completed
A44: NS-202606-0043 | B44: Ridgeway Plastics | C44: INV-413118 | D44: 1191.1 | E44: Facilities | F44: PO | G44: PO-89299 | H44: Grace Morgan | I44: Department Manager | J44: 46181 | K44: Net 15 | L44: 46196 | M44: Sent to Accounting | N44: Missing Documentation | O44: 46189 | Q44: =IF(J44="","",TODAY()-J44) -> 8 | R44: =IF(O44="","",O44-J44) -> 8 | S44: =IF(L44="","",L44-TODAY()) -> 7 | T44: =IF(AND(M44="Pending Approval",Q44>5),"Overdue","On Track") -> On Track | U44: =IF(AND(M44<>"Paid",S44<=5),"At Risk","Normal") -> Normal | V44: Exception review required: Missing Documentation
A45: NS-202606-0044 | B45: Metro Waste Services | C45: INV-936912 | D45: 3592.58 | E45: Engineering | F45: Non-PO | H45: Maya Singh | I45: Department Manager | J45: 46158 | K45: 2/10 Net 30 | L45: 46188 | M45: Paid | N45: None | O45: 46163 | P45: 46169 | Q45: =IF(J45="","",TODAY()-J45) -> 31 | R45: =IF(O45="","",O45-J45) -> 5 | S45: =IF(L45="","",L45-TODAY()) -> -1 | T45: =IF(AND(M45="Pending Approval",Q45>5),"Overdue","On Track") -> On Track | U45: =IF(AND(M45<>"Paid",S45<=5),"At Risk","Normal") -> Normal | V45: Payment completed
A46: NS-202606-0045 | B46: Metro Waste Services | C46: INV-242291 | D46: 2376.63 | E46: Sales | F46: PO | G46: PO-70780 | H46: Ryan Scott | I46: Department Manager | J46: 46178 | K46: Net 15 | L46: 46193 | M46: Pending Approval | N46: Duplicate Invoice | Q46: =IF(J46="","",TODAY()-J46) -> 11 | R46: =IF(O46="","",O46-J46) | S46: =IF(L46="","",L46-TODAY()) -> 4 | T46: =IF(AND(M46="Pending Approval",Q46>5),"Overdue","On Track") -> Overdue | U46: =IF(AND(M46<>"Paid",S46<=5),"At Risk","Normal") -> At Risk | V46: Exception review required: Duplicate Invoice
A47: NS-202606-0046 | B47: Orion Consulting | C47: INV-593152 | D47: 1974.92 | E47: Procurement | F47: PO | G47: PO-51420 | H47: Nina Patel | I47: Department Manager | J47: 46165 | K47: 2/10 Net 30 | L47: 46195 | M47: Paid | N47: None | O47: 46172 | P47: 46173 | Q47: =IF(J47="","",TODAY()-J47) -> 24 | R47: =IF(O47="","",O47-J47) -> 7 | S47: =IF(L47="","",L47-TODAY()) -> 6 | T47: =IF(AND(M47="Pending Approval",Q47>5),"Overdue","On Track") -> On Track | U47: =IF(AND(M47<>"Paid",S47<=5),"At Risk","Normal") -> Normal | V47: Payment completed
A48: NS-202606-0047 | B48: Apex Industrial Supply | C48: INV-350132 | D48: 4799.58 | E48: Sales | F48: PO | G48: PO-72607 | H48: Ryan Scott | I48: Department Manager | J48: 46148 | K48: Net 15 | L48: 46163 | M48: Paid | N48: Missing Documentation | O48: 46161 | P48: 46163 | Q48: =IF(J48="","",TODAY()-J48) -> 41 | R48: =IF(O48="","",O48-J48) -> 13 | S48: =IF(L48="","",L48-TODAY()) -> -26 | T48: =IF(AND(M48="Pending Approval",Q48>5),"Overdue","On Track") -> On Track | U48: =IF(AND(M48<>"Paid",S48<=5),"At Risk","Normal") -> Normal | V48: Exception review required: Missing Documentation
A49: NS-202606-0048 | B49: Evergreen Maintenance | C49: INV-426147 | D49: 2816.06 | E49: Facilities | F49: PO | G49: PO-75840 | H49: Grace Morgan | I49: Department Manager | J49: 46160 | K49: Net 45 | L49: 46205 | M49: Paid | N49: None | O49: 46163 | P49: 46165 | Q49: =IF(J49="","",TODAY()-J49) -> 29 | R49: =IF(O49="","",O49-J49) -> 3 | S49: =IF(L49="","",L49-TODAY()) -> 16 | T49: =IF(AND(M49="Pending Approval",Q49>5),"Overdue","On Track") -> On Track | U49: =IF(AND(M49<>"Paid",S49<=5),"At Risk","Normal") -> Normal | V49: Payment completed
A50: NS-202606-0049 | B50: Delta Tooling | C50: INV-354646 | D50: 1669.41 | E50: HR | F50: Non-PO | H50: Ava Johnson | I50: Department Manager | J50: 46168 | K50: 2/10 Net 30 | L50: 46198 | M50: Paid | N50: Unclear Department Ownership | O50: 46180 | P50: 46186 | Q50: =IF(J50="","",TODAY()-J50) -> 21 | R50: =IF(O50="","",O50-J50) -> 12 | S50: =IF(L50="","",L50-TODAY()) -> 9 | T50: =IF(AND(M50="Pending Approval",Q50>5),"Overdue","On Track") -> On Track | U50: =IF(AND(M50<>"Paid",S50<=5),"At Risk","Normal") -> Normal | V50: Exception review required: Unclear Department Ownership
A51: NS-202606-0050 | B51: Delta Tooling | C51: INV-113266 | D51: 21580.72 | E51: Sales | F51: Non-PO | H51: Michelle Young | I51: Director | J51: 46151 | K51: Net 15 | L51: 46166 | M51: Paid | N51: None | O51: 46158 | P51: 46161 | Q51: =IF(J51="","",TODAY()-J51) -> 38 | R51: =IF(O51="","",O51-J51) -> 7 | S51: =IF(L51="","",L51-TODAY()) -> -23 | T51: =IF(AND(M51="Pending Approval",Q51>5),"Overdue","On Track") -> On Track | U51: =IF(AND(M51<>"Paid",S51<=5),"At Risk","Normal") -> Normal | V51: Payment completed
A52: NS-202606-0051 | B52: Northfield Metals | C52: INV-965845 | D52: 4621.58 | E52: Facilities | F52: Non-PO | H52: Grace Morgan | I52: Department Manager | J52: 46173 | K52: Net 30 | L52: 46203 | M52: Sent to Accounting | N52: None | O52: 46184 | Q52: =IF(J52="","",TODAY()-J52) -> 16 | R52: =IF(O52="","",O52-J52) -> 11 | S52: =IF(L52="","",L52-TODAY()) -> 14 | T52: =IF(AND(M52="Pending Approval",Q52>5),"Overdue","On Track") -> On Track | U52: =IF(AND(M52<>"Paid",S52<=5),"At Risk","Normal") -> Normal
A53: NS-202606-0052 | B53: Zenith Software | C53: INV-452737 | D53: 4125.29 | E53: HR | F53: Non-PO | H53: Ava Johnson | I53: Department Manager | J53: 46149 | K53: Net 45 | L53: 46194 | M53: Paid | N53: Incorrect Vendor Information | O53: 46164 | P53: 46168 | Q53: =IF(J53="","",TODAY()-J53) -> 40 | R53: =IF(O53="","",O53-J53) -> 15 | S53: =IF(L53="","",L53-TODAY()) -> 5 | T53: =IF(AND(M53="Pending Approval",Q53>5),"Overdue","On Track") -> On Track | U53: =IF(AND(M53<>"Paid",S53<=5),"At Risk","Normal") -> Normal | V53: Exception review required: Incorrect Vendor Information
A54: NS-202606-0053 | B54: Apex Industrial Supply | C54: INV-300337 | D54: 8545.88 | E54: Facilities | F54: PO | G54: PO-82286 | H54: Victor Allen | I54: Director | J54: 46160 | K54: Net 45 | L54: 46205 | M54: Paid | N54: None | O54: 46168 | P54: 46173 | Q54: =IF(J54="","",TODAY()-J54) -> 29 | R54: =IF(O54="","",O54-J54) -> 8 | S54: =IF(L54="","",L54-TODAY()) -> 16 | T54: =IF(AND(M54="Pending Approval",Q54>5),"Overdue","On Track") -> On Track | U54: =IF(AND(M54<>"Paid",S54<=5),"At Risk","Normal") -> Normal | V54: Payment completed
A55: NS-202606-0054 | B55: Cedar Packaging Co. | C55: INV-524045 | D55: 14527.27 | E55: Production | F55: Non-PO | H55: Heather King | I55: Director | J55: 46188 | K55: 2/10 Net 30 | L55: 46218 | M55: Pending Approval | N55: None | Q55: =IF(J55="","",TODAY()-J55) -> 1 | R55: =IF(O55="","",O55-J55) | S55: =IF(L55="","",L55-TODAY()) -> 29 | T55: =IF(AND(M55="Pending Approval",Q55>5),"Overdue","On Track") -> On Track | U55: =IF(AND(M55<>"Paid",S55<=5),"At Risk","Normal") -> Normal | V55: Awaiting manager/director action
A56: NS-202606-0055 | B56: WestBridge Staffing | C56: INV-421517 | D56: 2896.08 | E56: Production | F56: PO | G56: PO-64794 | H56: Ethan Brooks | I56: Department Manager | J56: 46166 | K56: 2/10 Net 30 | L56: 46196 | M56: Paid | N56: Unclear Department Ownership | O56: 46180 | P56: 46183 | Q56: =IF(J56="","",TODAY()-J56) -> 23 | R56: =IF(O56="","",O56-J56) -> 14 | S56: =IF(L56="","",L56-TODAY()) -> 7 | T56: =IF(AND(M56="Pending Approval",Q56>5),"Overdue","On Track") -> On Track | U56: =IF(AND(M56<>"Paid",S56<=5),"At Risk","Normal") -> Normal | V56: Exception review required: Unclear Department Ownership
A57: NS-202606-0056 | B57: IronGate Components | C57: INV-718226 | D57: 1126.26 | E57: Production | F57: PO | G57: PO-65118 | H57: Ethan Brooks | I57: Department Manager | J57: 46188 | K57: Net 30 | L57: 46218 | M57: Pending Approval | N57: None | Q57: =IF(J57="","",TODAY()-J57) -> 1 | R57: =IF(O57="","",O57-J57) | S57: =IF(L57="","",L57-TODAY()) -> 29 | T57: =IF(AND(M57="Pending Approval",Q57>5),"Overdue","On Track") -> On Track | U57: =IF(AND(M57<>"Paid",S57<=5),"At Risk","Normal") -> Normal | V57: Awaiting manager/director action
A58: NS-202606-0057 | B58: Quarry Equipment Rental | C58: INV-680238 | D58: 707.39 | E58: HR | F58: PO | G58: PO-44908 | H58: Ava Johnson | I58: Department Manager | J58: 46167 | K58: Net 30 | L58: 46197 | M58: Paid | N58: None | O58: 46170 | P58: 46171 | Q58: =IF(J58="","",TODAY()-J58) -> 22 | R58: =IF(O58="","",O58-J58) -> 3 | S58: =IF(L58="","",L58-TODAY()) -> 8 | T58: =IF(AND(M58="Pending Approval",Q58>5),"Overdue","On Track") -> On Track | U58: =IF(AND(M58<>"Paid",S58<=5),"At Risk","Normal") -> Normal | V58: Payment completed
A59: NS-202606-0058 | B59: Juniper Office Supply | C59: INV-364742 | D59: 69831.94 | E59: Sales | F59: Non-PO | H59: Jordan Blake | I59: Finance Director | J59: 46150 | K59: Net 15 | L59: 46165 | M59: Paid | N59: None | O59: 46166 | P59: 46167 | Q59: =IF(J59="","",TODAY()-J59) -> 39 | R59: =IF(O59="","",O59-J59) -> 16 | S59: =IF(L59="","",L59-TODAY()) -> -24 | T59: =IF(AND(M59="Pending Approval",Q59>5),"Overdue","On Track") -> On Track | U59: =IF(AND(M59<>"Paid",S59<=5),"At Risk","Normal") -> Normal | V59: Payment completed
A60: NS-202606-0059 | B60: Pioneer MRO | C60: INV-360247 | D60: 12813.8 | E60: Maintenance | F60: PO | G60: PO-71251 | H60: Priya Shah | I60: Director | J60: 46187 | K60: Net 15 | L60: 46202 | M60: Pending Approval | N60: None | Q60: =IF(J60="","",TODAY()-J60) -> 2 | R60: =IF(O60="","",O60-J60) | S60: =IF(L60="","",L60-TODAY()) -> 13 | T60: =IF(AND(M60="Pending Approval",Q60>5),"Overdue","On Track") -> On Track | U60: =IF(AND(M60<>"Paid",S60<=5),"At Risk","Normal") -> Normal | V60: Awaiting manager/director action
A61: NS-202606-0060 | B61: Delta Tooling | C61: INV-739244 | D61: 16823.19 | E61: IT | F61: Non-PO | H61: Monica Price | I61: Director | J61: 46158 | K61: 2/10 Net 30 | L61: 46188 | M61: Paid | N61: None | O61: 46168 | P61: 46169 | Q61: =IF(J61="","",TODAY()-J61) -> 31 | R61: =IF(O61="","",O61-J61) -> 10 | S61: =IF(L61="","",L61-TODAY()) -> -1 | T61: =IF(AND(M61="Pending Approval",Q61>5),"Overdue","On Track") -> On Track | U61: =IF(AND(M61<>"Paid",S61<=5),"At Risk","Normal") -> Normal | V61: Payment completed
A62: NS-202606-0061 | B62: Zenith Software | C62: INV-572387 | D62: 39941.26 | E62: Maintenance | F62: PO | G62: PO-73281 | H62: Jordan Blake | I62: Finance Director | J62: 46149 | K62: Net 30 | L62: 46179 | M62: Paid | N62: None | O62: 46153 | P62: 46157 | Q62: =IF(J62="","",TODAY()-J62) -> 40 | R62: =IF(O62="","",O62-J62) -> 4 | S62: =IF(L62="","",L62-TODAY()) -> -10 | T62: =IF(AND(M62="Pending Approval",Q62>5),"Overdue","On Track") -> On Track | U62: =IF(AND(M62<>"Paid",S62<=5),"At Risk","Normal") -> Normal | V62: Payment completed
A63: NS-202606-0062 | B63: WestBridge Staffing | C63: INV-926097 | D63: 398.51 | E63: HR | F63: PO | G63: PO-48528 | H63: Ava Johnson | I63: Department Manager | J63: 46188 | K63: 2/10 Net 30 | L63: 46218 | M63: Sent to Accounting | N63: None | O63: 46189 | Q63: =IF(J63="","",TODAY()-J63) -> 1 | R63: =IF(O63="","",O63-J63) -> 1 | S63: =IF(L63="","",L63-TODAY()) -> 29 | T63: =IF(AND(M63="Pending Approval",Q63>5),"Overdue","On Track") -> On Track | U63: =IF(AND(M63<>"Paid",S63<=5),"At Risk","Normal") -> Normal
A64: NS-202606-0063 | B64: Union Energy Services | C64: INV-422554 | D64: 4498.19 | E64: HR | F64: PO | G64: PO-65688 | H64: Ava Johnson | I64: Department Manager | J64: 46158 | K64: Net 30 | L64: 46188 | M64: Paid | N64: Duplicate Invoice | O64: 46164 | P64: 46171 | Q64: =IF(J64="","",TODAY()-J64) -> 31 | R64: =IF(O64="","",O64-J64) -> 6 | S64: =IF(L64="","",L64-TODAY()) -> -1 | T64: =IF(AND(M64="Pending Approval",Q64>5),"Overdue","On Track") -> On Track | U64: =IF(AND(M64<>"Paid",S64<=5),"At Risk","Normal") -> Normal | V64: Exception review required: Duplicate Invoice
A65: NS-202606-0064 | B65: Titan Machine Parts | C65: INV-617781 | D65: 22963.25 | E65: Sales | F65: PO | G65: PO-60716 | H65: Michelle Young | I65: Director | J65: 46188 | K65: Net 45 | L65: 46233 | M65: Exception | N65: None | Q65: =IF(J65="","",TODAY()-J65) -> 1 | R65: =IF(O65="","",O65-J65) | S65: =IF(L65="","",L65-TODAY()) -> 44 | T65: =IF(AND(M65="Pending Approval",Q65>5),"Overdue","On Track") -> On Track | U65: =IF(AND(M65<>"Paid",S65<=5),"At Risk","Normal") -> Normal
A66: NS-202606-0065 | B66: Orion Consulting | C66: INV-900177 | D66: 4296.87 | E66: Maintenance | F66: Non-PO | H66: Marcus Lee | I66: Department Manager | J66: 46182 | K66: Net 45 | L66: 46227 | M66: Pending Approval | N66: None | Q66: =IF(J66="","",TODAY()-J66) -> 7 | R66: =IF(O66="","",O66-J66) | S66: =IF(L66="","",L66-TODAY()) -> 38 | T66: =IF(AND(M66="Pending Approval",Q66>5),"Overdue","On Track") -> Overdue | U66: =IF(AND(M66<>"Paid",S66<=5),"At Risk","Normal") -> Normal | V66: Awaiting manager/director action
A67: NS-202606-0066 | B67: ForgeWorks Materials | C67: INV-436653 | D67: 2262.14 | E67: Facilities | F67: PO | G67: PO-68360 | H67: Grace Morgan | I67: Department Manager | J67: 46171 | K67: 2/10 Net 30 | L67: 46201 | M67: Sent to Accounting | N67: Unclear Department Ownership | O67: 46186 | Q67: =IF(J67="","",TODAY()-J67) -> 18 | R67: =IF(O67="","",O67-J67) -> 15 | S67: =IF(L67="","",L67-TODAY()) -> 12 | T67: =IF(AND(M67="Pending Approval",Q67>5),"Overdue","On Track") -> On Track | U67: =IF(AND(M67<>"Paid",S67<=5),"At Risk","Normal") -> Normal | V67: Exception review required: Unclear Department Ownership
A68: NS-202606-0067 | B68: Vector Calibration | C68: INV-221552 | D68: 11431.17 | E68: Maintenance | F68: Non-PO | H68: Priya Shah | I68: Director | J68: 46162 | K68: 2/10 Net 30 | L68: 46192 | M68: Paid | N68: Missing PO | O68: 46180 | P68: 46183 | Q68: =IF(J68="","",TODAY()-J68) -> 27 | R68: =IF(O68="","",O68-J68) -> 18 | S68: =IF(L68="","",L68-TODAY()) -> 3 | T68: =IF(AND(M68="Pending Approval",Q68>5),"Overdue","On Track") -> On Track | U68: =IF(AND(M68<>"Paid",S68<=5),"At Risk","Normal") -> Normal | V68: Exception review required: Missing PO
A69: NS-202606-0068 | B69: Metro Waste Services | C69: INV-313446 | D69: 5022.45 | E69: IT | F69: Non-PO | H69: Monica Price | I69: Director | J69: 46173 | K69: 2/10 Net 30 | L69: 46203 | M69: Pending Approval | N69: None | Q69: =IF(J69="","",TODAY()-J69) -> 16 | R69: =IF(O69="","",O69-J69) | S69: =IF(L69="","",L69-TODAY()) -> 14 | T69: =IF(AND(M69="Pending Approval",Q69>5),"Overdue","On Track") -> Overdue | U69: =IF(AND(M69<>"Paid",S69<=5),"At Risk","Normal") -> Normal | V69: Awaiting manager/director action
A70: NS-202606-0069 | B70: IronGate Components | C70: INV-679077 | D70: 1560.53 | E70: IT | F70: Non-PO | H70: Noah Bennett | I70: Department Manager | J70: 46175 | K70: Net 15 | L70: 46190 | M70: Paid | N70: None | O70: 46181 | P70: 46182 | Q70: =IF(J70="","",TODAY()-J70) -> 14 | R70: =IF(O70="","",O70-J70) -> 6 | S70: =IF(L70="","",L70-TODAY()) -> 1 | T70: =IF(AND(M70="Pending Approval",Q70>5),"Overdue","On Track") -> On Track | U70: =IF(AND(M70<>"Paid",S70<=5),"At Risk","Normal") -> Normal | V70: Payment completed
A71: NS-202606-0070 | B71: Northfield Metals | C71: INV-386706 | D71: 4078.4 | E71: Maintenance | F71: PO | G71: PO-37698 | H71: Marcus Lee | I71: Department Manager | J71: 46185 | K71: Net 30 | L71: 46215 | M71: Exception | N71: None | Q71: =IF(J71="","",TODAY()-J71) -> 4 | R71: =IF(O71="","",O71-J71) | S71: =IF(L71="","",L71-TODAY()) -> 26 | T71: =IF(AND(M71="Pending Approval",Q71>5),"Overdue","On Track") -> On Track | U71: =IF(AND(M71<>"Paid",S71<=5),"At Risk","Normal") -> Normal
A72: NS-202606-0071 | B72: Northfield Metals | C72: INV-535098 | D72: 42439.3 | E72: Facilities | F72: PO | G72: PO-55138 | H72: Jordan Blake | I72: Finance Director | J72: 46156 | K72: Net 30 | L72: 46186 | M72: Sent to Accounting | N72: Missing Documentation | O72: 46179 | Q72: =IF(J72="","",TODAY()-J72) -> 33 | R72: =IF(O72="","",O72-J72) -> 23 | S72: =IF(L72="","",L72-TODAY()) -> -3 | T72: =IF(AND(M72="Pending Approval",Q72>5),"Overdue","On Track") -> On Track | U72: =IF(AND(M72<>"Paid",S72<=5),"At Risk","Normal") -> At Risk | V72: Exception review required: Missing Documentation
A73: NS-202606-0072 | B73: Keystone Electrical | C73: INV-669827 | D73: 261.67 | E73: IT | F73: Non-PO | H73: Noah Bennett | I73: Department Manager | J73: 46181 | K73: 2/10 Net 30 | L73: 46211 | M73: Sent to Accounting | N73: Missing Documentation | O73: 46189 | Q73: =IF(J73="","",TODAY()-J73) -> 8 | R73: =IF(O73="","",O73-J73) -> 8 | S73: =IF(L73="","",L73-TODAY()) -> 22 | T73: =IF(AND(M73="Pending Approval",Q73>5),"Overdue","On Track") -> On Track | U73: =IF(AND(M73<>"Paid",S73<=5),"At Risk","Normal") -> Normal | V73: Exception review required: Missing Documentation
A74: NS-202606-0073 | B74: Metro Waste Services | C74: INV-950823 | D74: 21957.23 | E74: Facilities | F74: Non-PO | H74: Victor Allen | I74: Director | J74: 46159 | K74: 2/10 Net 30 | L74: 46189 | M74: Paid | N74: None | O74: 46166 | P74: 46172 | Q74: =IF(J74="","",TODAY()-J74) -> 30 | R74: =IF(O74="","",O74-J74) -> 7 | S74: =IF(L74="","",L74-TODAY()) -> 0 | T74: =IF(AND(M74="Pending Approval",Q74>5),"Overdue","On Track") -> On Track | U74: =IF(AND(M74<>"Paid",S74<=5),"At Risk","Normal") -> Normal | V74: Payment completed
A75: NS-202606-0074 | B75: Metro Waste Services | C75: INV-561694 | D75: 80571.36 | E75: Engineering | F75: Non-PO | H75: Jordan Blake | I75: Finance Director | J75: 46153 | K75: 2/10 Net 30 | L75: 46183 | M75: Paid | N75: Unclear Department Ownership | O75: 46174 | P75: 46181 | Q75: =IF(J75="","",TODAY()-J75) -> 36 | R75: =IF(O75="","",O75-J75) -> 21 | S75: =IF(L75="","",L75-TODAY()) -> -6 | T75: =IF(AND(M75="Pending Approval",Q75>5),"Overdue","On Track") -> On Track | U75: =IF(AND(M75<>"Paid",S75<=5),"At Risk","Normal") -> Normal | V75: Exception review required: Unclear Department Ownership
A76: NS-202606-0075 | B76: Delta Tooling | C76: INV-826353 | D76: 5299.28 | E76: IT | F76: PO | G76: PO-87077 | H76: Monica Price | I76: Director | J76: 46185 | K76: Net 30 | L76: 46215 | M76: Pending Approval | N76: None | Q76: =IF(J76="","",TODAY()-J76) -> 4 | R76: =IF(O76="","",O76-J76) | S76: =IF(L76="","",L76-TODAY()) -> 26 | T76: =IF(AND(M76="Pending Approval",Q76>5),"Overdue","On Track") -> On Track | U76: =IF(AND(M76<>"Paid",S76<=5),"At Risk","Normal") -> Normal | V76: Awaiting manager/director action
A77: NS-202606-0076 | B77: Metro Waste Services | C77: INV-817644 | D77: 1744.97 | E77: Finance | F77: Non-PO | H77: Evelyn Carter | I77: Department Manager | J77: 46178 | K77: 2/10 Net 30 | L77: 46208 | M77: Sent to Accounting | N77: Unclear Department Ownership | O77: 46189 | Q77: =IF(J77="","",TODAY()-J77) -> 11 | R77: =IF(O77="","",O77-J77) -> 11 | S77: =IF(L77="","",L77-TODAY()) -> 19 | T77: =IF(AND(M77="Pending Approval",Q77>5),"Overdue","On Track") -> On Track | U77: =IF(AND(M77<>"Paid",S77<=5),"At Risk","Normal") -> Normal | V77: Exception review required: Unclear Department Ownership
A78: NS-202606-0077 | B78: Juniper Office Supply | C78: INV-148225 | D78: 13462.44 | E78: Production | F78: PO | G78: PO-71533 | H78: Heather King | I78: Director | J78: 46189 | K78: Net 15 | L78: 46204 | M78: Sent to Accounting | N78: None | O78: 46189 | Q78: =IF(J78="","",TODAY()-J78) -> 0 | R78: =IF(O78="","",O78-J78) -> 0 | S78: =IF(L78="","",L78-TODAY()) -> 15 | T78: =IF(AND(M78="Pending Approval",Q78>5),"Overdue","On Track") -> On Track | U78: =IF(AND(M78<>"Paid",S78<=5),"At Risk","Normal") -> Normal
A79: NS-202606-0078 | B79: Keystone Electrical | C79: INV-501126 | D79: 1955.53 | E79: Operations | F79: PO | G79: PO-64810 | H79: Olivia Grant | I79: Department Manager | J79: 46170 | K79: Net 30 | L79: 46200 | M79: Pending Approval | N79: None | Q79: =IF(J79="","",TODAY()-J79) -> 19 | R79: =IF(O79="","",O79-J79) | S79: =IF(L79="","",L79-TODAY()) -> 11 | T79: =IF(AND(M79="Pending Approval",Q79>5),"Overdue","On Track") -> Overdue | U79: =IF(AND(M79<>"Paid",S79<=5),"At Risk","Normal") -> Normal | V79: Awaiting manager/director action
A80: NS-202606-0079 | B80: Titan Machine Parts | C80: INV-587853 | D80: 4403.37 | E80: Finance | F80: PO | G80: PO-60221 | H80: Evelyn Carter | I80: Department Manager | J80: 46184 | K80: Net 45 | L80: 46229 | M80: Approved | N80: None | O80: 46185 | Q80: =IF(J80="","",TODAY()-J80) -> 5 | R80: =IF(O80="","",O80-J80) -> 1 | S80: =IF(L80="","",L80-TODAY()) -> 40 | T80: =IF(AND(M80="Pending Approval",Q80>5),"Overdue","On Track") -> On Track | U80: =IF(AND(M80<>"Paid",S80<=5),"At Risk","Normal") -> Normal
A81: NS-202606-0080 | B81: Juniper Office Supply | C81: INV-308894 | D81: 586.07 | E81: Finance | F81: Non-PO | H81: Evelyn Carter | I81: Department Manager | J81: 46181 | K81: Net 45 | L81: 46226 | M81: Exception | N81: None | Q81: =IF(J81="","",TODAY()-J81) -> 8 | R81: =IF(O81="","",O81-J81) | S81: =IF(L81="","",L81-TODAY()) -> 37 | T81: =IF(AND(M81="Pending Approval",Q81>5),"Overdue","On Track") -> On Track | U81: =IF(AND(M81<>"Paid",S81<=5),"At Risk","Normal") -> Normal
A82: NS-202606-0081 | B82: Metro Waste Services | C82: INV-693419 | D82: 1985.21 | E82: Facilities | F82: PO | G82: PO-49390 | H82: Grace Morgan | I82: Department Manager | J82: 46188 | K82: Net 45 | L82: 46233 | M82: Pending Approval | N82: None | Q82: =IF(J82="","",TODAY()-J82) -> 1 | R82: =IF(O82="","",O82-J82) | S82: =IF(L82="","",L82-TODAY()) -> 44 | T82: =IF(AND(M82="Pending Approval",Q82>5),"Overdue","On Track") -> On Track | U82: =IF(AND(M82<>"Paid",S82<=5),"At Risk","Normal") -> Normal | V82: Awaiting manager/director action
A83: NS-202606-0082 | B83: Vector Calibration | C83: INV-904751 | D83: 88787.88 | E83: Sales | F83: Non-PO | H83: Jordan Blake | I83: Finance Director | J83: 46162 | K83: Net 30 | L83: 46192 | M83: Paid | N83: None | O83: 46172 | P83: 46178 | Q83: =IF(J83="","",TODAY()-J83) -> 27 | R83: =IF(O83="","",O83-J83) -> 10 | S83: =IF(L83="","",L83-TODAY()) -> 3 | T83: =IF(AND(M83="Pending Approval",Q83>5),"Overdue","On Track") -> On Track | U83: =IF(AND(M83<>"Paid",S83<=5),"At Risk","Normal") -> Normal | V83: Payment completed
A84: NS-202606-0083 | B84: Vector Calibration | C84: INV-409445 | D84: 17250.84 | E84: Finance | F84: Non-PO | H84: Finance Director | I84: Director | J84: 46185 | K84: Net 15 | L84: 46200 | M84: Pending Approval | N84: None | Q84: =IF(J84="","",TODAY()-J84) -> 4 | R84: =IF(O84="","",O84-J84) | S84: =IF(L84="","",L84-TODAY()) -> 11 | T84: =IF(AND(M84="Pending Approval",Q84>5),"Overdue","On Track") -> On Track | U84: =IF(AND(M84<>"Paid",S84<=5),"At Risk","Normal") -> Normal | V84: Awaiting manager/director action
A85: NS-202606-0084 | B85: Keystone Electrical | C85: INV-455168 | D85: 1163.62 | E85: Sales | F85: Non-PO | H85: Ryan Scott | I85: Department Manager | J85: 46167 | K85: Net 45 | L85: 46212 | M85: Sent to Accounting | N85: Missing Documentation | O85: 46185 | Q85: =IF(J85="","",TODAY()-J85) -> 22 | R85: =IF(O85="","",O85-J85) -> 18 | S85: =IF(L85="","",L85-TODAY()) -> 23 | T85: =IF(AND(M85="Pending Approval",Q85>5),"Overdue","On Track") -> On Track | U85: =IF(AND(M85<>"Paid",S85<=5),"At Risk","Normal") -> Normal | V85: Exception review required: Missing Documentation
A86: NS-202606-0085 | B86: Delta Tooling | C86: INV-377304 | D86: 35282.61 | E86: Facilities | F86: Non-PO | H86: Jordan Blake | I86: Finance Director | J86: 46187 | K86: 2/10 Net 30 | L86: 46217 | M86: Pending Approval | N86: Unclear Department Ownership | Q86: =IF(J86="","",TODAY()-J86) -> 2 | R86: =IF(O86="","",O86-J86) | S86: =IF(L86="","",L86-TODAY()) -> 28 | T86: =IF(AND(M86="Pending Approval",Q86>5),"Overdue","On Track") -> On Track | U86: =IF(AND(M86<>"Paid",S86<=5),"At Risk","Normal") -> Normal | V86: Exception review required: Unclear Department Ownership
A87: NS-202606-0086 | B87: Ridgeway Plastics | C87: INV-749641 | D87: 3311.37 | E87: Maintenance | F87: Non-PO | H87: Marcus Lee | I87: Department Manager | J87: 46181 | K87: 2/10 Net 30 | L87: 46211 | M87: Sent to Accounting | N87: Missing Documentation | O87: 46189 | Q87: =IF(J87="","",TODAY()-J87) -> 8 | R87: =IF(O87="","",O87-J87) -> 8 | S87: =IF(L87="","",L87-TODAY()) -> 22 | T87: =IF(AND(M87="Pending Approval",Q87>5),"Overdue","On Track") -> On Track | U87: =IF(AND(M87<>"Paid",S87<=5),"At Risk","Normal") -> Normal | V87: Exception review required: Missing Documentation
A88: NS-202606-0087 | B88: Ridgeway Plastics | C88: INV-419149 | D88: 9316.66 | E88: Logistics | F88: PO | G88: PO-83992 | H88: Anthony Ross | I88: Director | J88: 46173 | K88: Net 45 | L88: 46218 | M88: Paid | N88: None | O88: 46175 | P88: 46176 | Q88: =IF(J88="","",TODAY()-J88) -> 16 | R88: =IF(O88="","",O88-J88) -> 2 | S88: =IF(L88="","",L88-TODAY()) -> 29 | T88: =IF(AND(M88="Pending Approval",Q88>5),"Overdue","On Track") -> On Track | U88: =IF(AND(M88<>"Paid",S88<=5),"At Risk","Normal") -> Normal | V88: Payment completed
A89: NS-202606-0088 | B89: Pioneer MRO | C89: INV-786735 | D89: 4287.03 | E89: Maintenance | F89: PO | G89: PO-59729 | H89: Marcus Lee | I89: Department Manager | J89: 46167 | K89: 2/10 Net 30 | L89: 46197 | M89: Approved | N89: None | O89: 46172 | Q89: =IF(J89="","",TODAY()-J89) -> 22 | R89: =IF(O89="","",O89-J89) -> 5 | S89: =IF(L89="","",L89-TODAY()) -> 8 | T89: =IF(AND(M89="Pending Approval",Q89>5),"Overdue","On Track") -> On Track | U89: =IF(AND(M89<>"Paid",S89<=5),"At Risk","Normal") -> Normal
A90: NS-202606-0089 | B90: Delta Tooling | C90: INV-204180 | D90: 4522.69 | E90: Facilities | F90: PO | G90: PO-75238 | H90: Grace Morgan | I90: Department Manager | J90: 46167 | K90: Net 30 | L90: 46197 | M90: Approved | N90: None | O90: 46172 | Q90: =IF(J90="","",TODAY()-J90) -> 22 | R90: =IF(O90="","",O90-J90) -> 5 | S90: =IF(L90="","",L90-TODAY()) -> 8 | T90: =IF(AND(M90="Pending Approval",Q90>5),"Overdue","On Track") -> On Track | U90: =IF(AND(M90<>"Paid",S90<=5),"At Risk","Normal") -> Normal
A91: NS-202606-0090 | B91: Vector Calibration | C91: INV-770556 | D91: 4699.18 | E91: Logistics | F91: PO | G91: PO-56092 | H91: Tyler Chen | I91: Department Manager | J91: 46161 | K91: Net 30 | L91: 46191 | M91: Paid | N91: Unclear Department Ownership | O91: 46172 | P91: 46178 | Q91: =IF(J91="","",TODAY()-J91) -> 28 | R91: =IF(O91="","",O91-J91) -> 11 | S91: =IF(L91="","",L91-TODAY()) -> 2 | T91: =IF(AND(M91="Pending Approval",Q91>5),"Overdue","On Track") -> On Track | U91: =IF(AND(M91<>"Paid",S91<=5),"At Risk","Normal") -> Normal | V91: Exception review required: Unclear Department Ownership
A92: NS-202606-0091 | B92: Titan Machine Parts | C92: INV-344316 | D92: 1767.47 | E92: Operations | F92: Non-PO | H92: Olivia Grant | I92: Department Manager | J92: 46180 | K92: Net 30 | L92: 46210 | M92: Pending Approval | N92: None | Q92: =IF(J92="","",TODAY()-J92) -> 9 | R92: =IF(O92="","",O92-J92) | S92: =IF(L92="","",L92-TODAY()) -> 21 | T92: =IF(AND(M92="Pending Approval",Q92>5),"Overdue","On Track") -> Overdue | U92: =IF(AND(M92<>"Paid",S92<=5),"At Risk","Normal") -> Normal | V92: Awaiting manager/director action
A93: NS-202606-0092 | B93: Keystone Electrical | C93: INV-928358 | D93: 16621.64 | E93: Procurement | F93: PO | G93: PO-39482 | H93: Carlos Mendes | I93: Director | J93: 46152 | K93: Net 45 | L93: 46197 | M93: Paid | N93: None | O93: 46153 | P93: 46156 | Q93: =IF(J93="","",TODAY()-J93) -> 37 | R93: =IF(O93="","",O93-J93) -> 1 | S93: =IF(L93="","",L93-TODAY()) -> 8 | T93: =IF(AND(M93="Pending Approval",Q93>5),"Overdue","On Track") -> On Track | U93: =IF(AND(M93<>"Paid",S93<=5),"At Risk","Normal") -> Normal | V93: Payment completed
A94: NS-202606-0093 | B94: Harbor Freight Services | C94: INV-479625 | D94: 1042.82 | E94: HR | F94: PO | G94: PO-78609 | H94: Ava Johnson | I94: Department Manager | J94: 46170 | K94: Net 15 | L94: 46185 | M94: Sent to Accounting | N94: None | O94: 46178 | Q94: =IF(J94="","",TODAY()-J94) -> 19 | R94: =IF(O94="","",O94-J94) -> 8 | S94: =IF(L94="","",L94-TODAY()) -> -4 | T94: =IF(AND(M94="Pending Approval",Q94>5),"Overdue","On Track") -> On Track | U94: =IF(AND(M94<>"Paid",S94<=5),"At Risk","Normal") -> At Risk
A95: NS-202606-0094 | B95: Quarry Equipment Rental | C95: INV-546980 | D95: 2542.47 | E95: HR | F95: Non-PO | H95: Ava Johnson | I95: Department Manager | J95: 46146 | K95: Net 45 | L95: 46191 | M95: Sent to Accounting | N95: None | O95: 46151 | Q95: =IF(J95="","",TODAY()-J95) -> 43 | R95: =IF(O95="","",O95-J95) -> 5 | S95: =IF(L95="","",L95-TODAY()) -> 2 | T95: =IF(AND(M95="Pending Approval",Q95>5),"Overdue","On Track") -> On Track | U95: =IF(AND(M95<>"Paid",S95<=5),"At Risk","Normal") -> At Risk
A96: NS-202606-0095 | B96: Vector Calibration | C96: INV-674993 | D96: 4389.14 | E96: Maintenance | F96: PO | G96: PO-35294 | H96: Marcus Lee | I96: Department Manager | J96: 46164 | K96: Net 30 | L96: 46194 | M96: Paid | N96: None | O96: 46171 | P96: 46176 | Q96: =IF(J96="","",TODAY()-J96) -> 25 | R96: =IF(O96="","",O96-J96) -> 7 | S96: =IF(L96="","",L96-TODAY()) -> 5 | T96: =IF(AND(M96="Pending Approval",Q96>5),"Overdue","On Track") -> On Track | U96: =IF(AND(M96<>"Paid",S96<=5),"At Risk","Normal") -> Normal | V96: Payment completed
A97: NS-202606-0096 | B97: WestBridge Staffing | C97: INV-782535 | D97: 2968.13 | E97: Logistics | F97: PO | G97: PO-63131 | H97: Tyler Chen | I97: Department Manager | J97: 46182 | K97: 2/10 Net 30 | L97: 46212 | M97: Exception | N97: None | Q97: =IF(J97="","",TODAY()-J97) -> 7 | R97: =IF(O97="","",O97-J97) | S97: =IF(L97="","",L97-TODAY()) -> 23 | T97: =IF(AND(M97="Pending Approval",Q97>5),"Overdue","On Track") -> On Track | U97: =IF(AND(M97<>"Paid",S97<=5),"At Risk","Normal") -> Normal
A98: NS-202606-0097 | B98: Ridgeway Plastics | C98: INV-427704 | D98: 13386.36 | E98: Sales | F98: Non-PO | H98: Michelle Young | I98: Director | J98: 46170 | K98: Net 45 | L98: 46215 | M98: Sent to Accounting | N98: Missing Documentation | O98: 46189 | Q98: =IF(J98="","",TODAY()-J98) -> 19 | R98: =IF(O98="","",O98-J98) -> 19 | S98: =IF(L98="","",L98-TODAY()) -> 26 | T98: =IF(AND(M98="Pending Approval",Q98>5),"Overdue","On Track") -> On Track | U98: =IF(AND(M98<>"Paid",S98<=5),"At Risk","Normal") -> Normal | V98: Exception review required: Missing Documentation
A99: NS-202606-0098 | B99: Vector Calibration | C99: INV-951201 | D99: 944.51 | E99: Quality | F99: Non-PO | H99: Lena Ortiz | I99: Department Manager | J99: 46148 | K99: Net 15 | L99: 46163 | M99: Paid | N99: Missing Documentation | O99: 46157 | P99: 46160 | Q99: =IF(J99="","",TODAY()-J99) -> 41 | R99: =IF(O99="","",O99-J99) -> 9 | S99: =IF(L99="","",L99-TODAY()) -> -26 | T99: =IF(AND(M99="Pending Approval",Q99>5),"Overdue","On Track") -> On Track | U99: =IF(AND(M99<>"Paid",S99<=5),"At Risk","Normal") -> Normal | V99: Exception review required: Missing Documentation
A100: NS-202606-0099 | B100: Evergreen Maintenance | C100: INV-856086 | D100: 4602.64 | E100: IT | F100: PO | G100: PO-73909 | H100: Noah Bennett | I100: Department Manager | J100: 46151 | K100: 2/10 Net 30 | L100: 46181 | M100: Approved | N100: None | O100: 46158 | Q100: =IF(J100="","",TODAY()-J100) -> 38 | R100: =IF(O100="","",O100-J100) -> 7 | S100: =IF(L100="","",L100-TODAY()) -> -8 | T100: =IF(AND(M100="Pending Approval",Q100>5),"Overdue","On Track") -> On Track | U100: =IF(AND(M100<>"Paid",S100<=5),"At Risk","Normal") -> At Risk
...

Sheet Lists
A1: Status | B1: Exception Type | C1: Invoice Type | D1: Payment Terms | E1: Department | F1: Approval Level
A2: Paid | B2: None | C2: PO | D2: Net 15 | E2: Operations | F2: Department Manager
A3: Sent to Accounting | B3: Missing PO | C3: Non-PO | D3: Net 30 | E3: Maintenance | F3: Director
A4: Approved | B4: Missing Documentation | D4: Net 45 | E4: Procurement | F4: Finance Director
A5: Pending Approval | B5: Incorrect Vendor Information | D5: 2/10 Net 30 | E5: Production
A6: Exception | B6: Duplicate Invoice | E6: Quality
A7: Rejected | B7: Unclear Department Ownership | E7: Logistics
E8: Engineering
E9: Facilities
E10: IT
E11: HR
E12: Finance
E13: Sales

Sheet KPI Dashboard
A1: NorthStar Manufacturing — Invoice Approval KPI Dashboard
A2: Dataset regenerated to align with case story: 1,200 invoices/month, ~60% PO, ~40% Non-PO, approval delays, late payment risk, and exception-driven rework.
A4: Metric | B4: Value | C4: Interpretation | E4: Approver | F4: Open Invoices | G4: Overdue Approvals | H4: Late Payment Risk | J4: Department | K4: Approved Count | L4: Avg Cycle Days | M4: Non-PO Count | O4: Exception Type | P4: Count
A5: Total Invoices | B5: =COUNTA('Invoice Tracker'!A2:A1201) -> 1200 | C5: Monthly invoice volume | E5: Lena Ortiz | F5: 45 | G5: 10 | H5: 10 | J5: Maintenance | K5: 85 | L5: 10.105882 | M5: 47 | O5: Unclear Department Ownership | P5: 124
A6: PO-Backed % | B6: =COUNTIF('Invoice Tracker'!F2:F1201,"PO")/COUNTA('Invoice Tracker'!A2:A1201) -> 0.605 | C6: Target story alignment: about 60% | E6: Marcus Lee | F6: 45 | G6: 11 | H6: 9 | J6: Production | K6: 64 | L6: 9.875 | M6: 40 | O6: Missing Documentation | P6: 114
A7: Non-PO % | B7: =COUNTIF('Invoice Tracker'!F2:F1201,"Non-PO")/COUNTA('Invoice Tracker'!A2:A1201) -> 0.395 | C7: Manual review exposure | E7: Grace Morgan | F7: 44 | G7: 9 | H7: 10 | J7: Facilities | K7: 79 | L7: 8.4177215 | M7: 43 | O7: Missing PO | P7: 59
A8: Open Invoices | B8: =COUNTIFS('Invoice Tracker'!M2:M1201,"<>Paid",'Invoice Tracker'!M2:M1201,"<>Rejected") -> 611 | C8: Current AP/approval backlog | E8: Jordan Blake | F8: 42 | G8: 6 | H8: 11 | J8: Operations | K8: 64 | L8: 8.40625 | M8: 34 | O8: Incorrect Vendor Information | P8: 37
A9: Overdue Approvals | B9: =COUNTIF('Invoice Tracker'!T2:T1201,"Overdue") -> 155 | C9: Approval SLA risk | E9: Ethan Brooks | F9: 41 | G9: 10 | H9: 12 | J9: IT | K9: 65 | L9: 7.9846154 | M9: 40 | O9: Duplicate Invoice | P9: 21
A10: Late Payment Risk | B10: =COUNTIF('Invoice Tracker'!U2:U1201,"At Risk") -> 154 | C10: Invoices near/past due and unpaid | E10: Noah Bennett | F10: 41 | G10: 12 | H10: 10 | J10: Engineering | K10: 75 | L10: 7.7866667 | M10: 38
A11: Late Paid Invoices | B11: =COUNTIF('Invoice Tracker'!#REF!,"Late") -> #REF! | C11: Confirmed late payments | E11: Tyler Chen | F11: 41 | G11: 13 | H11: 10 | J11: Finance | K11: 61 | L11: 7.6229508 | M11: 39
A12: Exception Rate | B12: =COUNTIF('Invoice Tracker'!N2:N1201,"<>None")/COUNTA('Invoice Tracker'!A2:A1201) -> 0.29583333 | C12: Rework/control risk | E12: Olivia Grant | F12: 41 | G12: 11 | H12: 6 | J12: Sales | K12: 81 | L12: 7.2592593 | M12: 44
A13: Avg Approval Cycle Days | B13: =AVERAGE('Invoice Tracker'!R2:R1201) -> 7.9584816 | C13: Receipt to approval | E13: Ava Johnson | F13: 37 | G13: 10 | H13: 13 | J13: Logistics | K13: 69 | L13: 7.0869565 | M13: 35
E14: Evelyn Carter | F14: 31 | G14: 7 | H14: 7 | J14: Procurement | K14: 69 | L14: 7.0289855 | M14: 38
J15: Quality | K15: 67 | L15: 6.9701493 | M15: 38
J16: HR | K16: 64 | L16: 6.53125 | M16: 38

Sheet Approval Matrix
A1: Department | B1: Department Manager | C1: Director | D1: < $5,000 | E1: $5,000-$25,000 | F1: > $25,000 | G1: Backup Approver | H1: Last Reviewed
A2: Operations | B2: Olivia Grant | C2: Daniel Reed | D2: Olivia Grant | E2: Daniel Reed | F2: Jordan Blake | G2: Delegated Backup Required | H2: 46189
A3: Maintenance | B3: Marcus Lee | C3: Priya Shah | D3: Marcus Lee | E3: Priya Shah | F3: Jordan Blake | G3: Delegated Backup Required | H3: 46189
A4: Procurement | B4: Nina Patel | C4: Carlos Mendes | D4: Nina Patel | E4: Carlos Mendes | F4: Jordan Blake | G4: Delegated Backup Required | H4: 46189
A5: Production | B5: Ethan Brooks | C5: Heather King | D5: Ethan Brooks | E5: Heather King | F5: Jordan Blake | G5: Delegated Backup Required | H5: 46189
A6: Quality | B6: Lena Ortiz | C6: Samantha Wu | D6: Lena Ortiz | E6: Samantha Wu | F6: Jordan Blake | G6: Delegated Backup Required | H6: 46189
A7: Logistics | B7: Tyler Chen | C7: Anthony Ross | D7: Tyler Chen | E7: Anthony Ross | F7: Jordan Blake | G7: Delegated Backup Required | H7: 46189
A8: Engineering | B8: Maya Singh | C8: Robert Hayes | D8: Maya Singh | E8: Robert Hayes | F8: Jordan Blake | G8: Delegated Backup Required | H8: 46189
A9: Facilities | B9: Grace Morgan | C9: Victor Allen | D9: Grace Morgan | E9: Victor Allen | F9: Jordan Blake | G9: Delegated Backup Required | H9: 46189
A10: IT | B10: Noah Bennett | C10: Monica Price | D10: Noah Bennett | E10: Monica Price | F10: Jordan Blake | G10: Delegated Backup Required | H10: 46189
A11: HR | B11: Ava Johnson | C11: Karen Lewis | D11: Ava Johnson | E11: Karen Lewis | F11: Jordan Blake | G11: Delegated Backup Required | H11: 46189
A12: Finance | B12: Evelyn Carter | C12: Finance Director | D12: Evelyn Carter | E12: Finance Director | F12: Jordan Blake | G12: Delegated Backup Required | H12: 46189
A13: Sales | B13: Ryan Scott | C13: Michelle Young | D13: Ryan Scott | E13: Michelle Young | F13: Jordan Blake | G13: Delegated Backup Required | H13: 46189

Sheet Exception Log
A1: Exception Type | B1: Invoice Count | C1: % of Total | D1: Primary Risk | E1: Recommended Action
A2: Unclear Department Ownership | B2: 124 | C2: 0.10333333 | D2: Routing delay risk | E2: Update department ownership in approval matrix.
A3: Missing Documentation | B3: 114 | C3: 0.095 | D3: Audit evidence risk | E3: Require supporting docs before approval task is issued.
A4: Missing PO | B4: 59 | C4: 0.049166667 | D4: Control / validation risk | E4: Require PO before routing or document approved non-PO exception.
A5: Incorrect Vendor Information | B5: 37 | C5: 0.030833333 | D5: Payment accuracy risk | E5: Validate vendor master data before approval.
A6: Duplicate Invoice | B6: 21 | C6: 0.0175 | D6: Duplicate payment risk | E6: Apply vendor + invoice number duplicate check.

Sheet Business Requirements
A1: ID | B1: Type | C1: Requirement | D1: Priority | E1: Release
A2: BR-1 | B2: Business | C2: Reduce manual AP coordination effort | D2: High | E2: MVP
A3: BR-2 | B3: Business | C3: Improve visibility into invoice status and approval aging | D3: High | E3: MVP
A4: BR-3 | B4: Business | C4: Reduce approval delays and late payment risk | D4: High | E4: MVP
A5: BR-4 | B5: Business | C5: Support approval rules based on department ownership and invoice amount | D5: High | E5: MVP
A6: BR-5 | B6: Business | C6: Support additional review for non-PO invoices | D6: High | E6: MVP
A7: BR-6 | B7: Business | C7: Improve audit readiness and evidence retrieval | D7: High | E7: Phase 2
A8: BR-7 | B8: Functional | C8: Capture vendor, invoice number, amount, department, approver, dates, status, exception, and comments | D8: High | E8: MVP
A9: BR-8 | B9: Functional | C9: Route invoices under $5,000 to Department Manager | D9: High | E9: Phase 2
A10: BR-9 | B10: Functional | C10: Route invoices from $5,000 to $25,000 to Director | D10: High | E10: Phase 2
A11: BR-10 | B11: Functional | C11: Route invoices over $25,000 to Finance Director | D11: High | E11: Phase 2
A12: BR-11 | B12: Functional | C12: Send automated reminders and escalations for overdue approvals | D12: High | E12: Phase 2
A13: BR-12 | B13: Non-Functional | C13: Use role-based access and maintain auditable approval history | D13: High | E13: Phase 2

Sheet User Stories
A1: ID | B1: Release | C1: User Role | D1: Capability | E1: Business Value | F1: Acceptance Criteria
A2: US-1 | B2: MVP | C2: AP Analyst | D2: Standardized invoice tracker | E2: Track invoice status, aging, and ownership consistently | F2: Tracker includes required fields; status values standardized; overdue invoices flagged; exception reason captured
A3: US-2 | B3: MVP | C3: AP Analyst | D3: Updated approval matrix | E3: Route invoices without repeated clarification | F3: Matrix includes department, manager, director, backup approver, thresholds, owner, and review date
A4: US-3 | B4: MVP | C4: Finance Manager | D4: Approval SLA | E4: Identify overdue approvals and create accountability | F4: SLA start point documented; overdue logic defined; escalation timing documented
A5: US-4 | B5: MVP | C5: Finance Director | D5: Weekly aging report | E5: See pending invoices, overdue approvals, and late payment risk | F5: Report shows pending invoices by approver, department, age, amount, and due date
A6: US-5 | B6: Phase 2 | C6: AP Analyst | D6: Automated routing | E6: Reduce time spent determining approvers | F6: Invoices route by department and amount; non-PO invoices flagged
A7: US-6 | B7: Phase 2 | C7: AP Analyst | D7: Automated reminders | E7: Reduce manual follow-up effort | F7: Reminders sent by SLA; reminder history visible
A8: US-7 | B8: Phase 2 | C8: Finance Manager | D8: Escalation workflow | E8: Prevent approvals from remaining stuck | F8: Escalations occur after overdue thresholds and are visible in reporting
A9: US-8 | B9: Phase 2 | C9: Auditor | D9: Approval audit trail | E9: Retrieve approval evidence efficiently | F9: Approval includes approver, date, decision, comments, supporting docs, and retention
A10: US-9 | B10: Future | C10: Finance Leadership | D10: Dynamics 365 workflow assessment | E10: Determine if ERP can support future-state workflow | F10: Workflow options, integration points, support needs, cost, and effort documented

Sheet Implementation Roadmap
A1: Phase | B1: Timeline | C1: Focus | D1: Key Activities | E1: Deliverables
A2: Phase 1 | B2: Days 1-30 | C2: Standardize and Stabilize | D2: Update approval policy; validate approval matrix; standardize tracker; define exceptions | E2: Updated policy, approval matrix, tracker, exception code list
A3: Phase 1 | B3: Days 31-60 | C3: Visibility and Accountability | D3: Define SLA; build aging report; establish KPI baseline; communicate manager expectations | E3: Approval SLA, weekly aging report, KPI baseline
A4: Phase 2 | B4: Days 61-90 | C4: Automation Preparation | D4: Document workflow requirements; define reminder/escalation rules; test pilot design | E4: Workflow requirements, test scenarios, pilot plan
A5: Phase 2 | B5: Days 91-150 | C5: Workflow Automation | D5: Configure routing, approval queue, reminders, escalations, audit trail, dashboard | E5: Automated workflow and dashboard
A6: Phase 3 | B6: Days 151+ | C6: Long-Term Platform Decision | D6: Assess Dynamics 365 workflow vs AP automation software | E6: Feasibility assessment, solution recommendation, implementation roadmap

Sheet Data Dictionary
A1: Field | B1: Definition
A2: Invoice ID | B2: Unique invoice tracking ID for the simulated NorthStar monthly dataset
A3: Invoice Amount | B3: Vendor invoice dollar value
A4: Invoice Type | B4: PO or Non-PO; target story alignment is approximately 60% PO and 40% Non-PO
A5: Approval Level | B5: Approver authority based on amount threshold
A6: Invoice Age Days | B6: Formula: TODAY() - Date Received
A7: Approval Cycle Days | B7: Formula: Approval Date - Date Received when approved
A8: Days Until Due | B8: Formula: Payment Due Date - TODAY()
A9: Overdue Approval Flag | B9: Formula-based flag when invoice is pending approval and older than SLA threshold
A10: Late Payment Risk | B10: Formula-based flag for unpaid invoices due within five days or past due
A11: Exception Type | B11: Common rework/control issue: Missing PO, Missing Documentation, Incorrect Vendor Information, Duplicate Invoice, Unclear Department Ownership
